{
    "keep": {
        "days": true,
        "amount": 14
    },
    "auditLog": "C:\\Users\\Harold Ligon\\Desktop\\MyMobileApps\\MoriahFaithConnect\\mmmbc\\admin\\logs\\.ad2caa0f6f66f581ece0b2854291650910053aba-audit.json",
    "files": [
        {
            "date": 1784657794415,
            "name": "C:\\Users\\Harold Ligon\\Desktop\\MyMobileApps\\MoriahFaithConnect\\mmmbc\\admin\\logs\\audit-2026-07-21.log",
            "hash": "9b896d0eb3e2cc295a39e461f76e5ba1394054549a77c7c286d26489c6440251"
        },
        {
            "date": 1784694029753,
            "name": "C:\\Users\\Harold Ligon\\Desktop\\MyMobileApps\\MoriahFaithConnect\\mmmbc\\admin\\logs\\audit-2026-07-22.log",
            "hash": "6dbb63c2254a30274132bf940701594404a8af691f79bfb050830143e3e66d77"
        }
    ],
    "hashType": "sha256"
}